environment_settings/__init__.py
environment_settings/environment_settings.py
environment_settings-0.0.3.dist-info/LICENSE.txt
environment_settings-0.0.3.dist-info/METADATA
environment_settings-0.0.3.dist-info/WHEEL
environment_settings-0.0.3.dist-info/top_level.txt
environment_settings-0.0.3.dist-info/RECORD
