Metadata-Version: 2.1
Name: environment-settings
Version: 0.0.3
Summary: Environment specific management of application configuration
Author-email: Adam Foster <affoster@gmail.com>
License: MIT License
Project-URL: homepage, https://github.com/m0nonoke/environment-settings
Project-URL: repository, https://github.com/m0nonoke/environment-settings
Keywords: configuration,settings,dotenv,environment
Classifier: Programming Language :: Python :: 3
Classifier: License :: OSI Approved :: MIT License
Classifier: Operating System :: OS Independent
Requires-Python: >=3.7
License-File: LICENSE.txt
Provides-Extra: test
Requires-Dist: pytest (>7.0.0) ; extra == 'test'
